fastlite/__init__.py
fastlite/_modidx.py
fastlite/core.py
fastlite/kw.py
fastlite-0.2.2.dist-info/licenses/LICENSE
fastlite-0.2.2.dist-info/METADATA
fastlite-0.2.2.dist-info/WHEEL
fastlite-0.2.2.dist-info/entry_points.txt
fastlite-0.2.2.dist-info/top_level.txt
fastlite-0.2.2.dist-info/RECORD
