Metadata-Version: 2.4
Name: fastlite
Version: 0.2.2
Summary: A bit of extra usability for sqlite
Home-page: https://github.com/AnswerDotAI/fastlite
Author: Jeremy Howard
Author-email: info@fast.ai
License: Apache Software License 2.0
Keywords: nbdev jupyter notebook python sqlite sql
Classifier: Development Status :: 4 - Beta
Classifier: Intended Audience :: Developers
Classifier: Natural Language :: English
Classifier: Programming Language :: Python :: 3.10
Classifier: Programming Language :: Python :: 3.11
Classifier: Programming Language :: Python :: 3.12
Classifier: License :: OSI Approved :: Apache Software License
Requires-Python: >=3.10
License-File: LICENSE
Requires-Dist: fastcore>=1.7.1
Requires-Dist: apswutils>=0.1.0
Provides-Extra: dev
Requires-Dist: graphviz; extra == "dev"
Dynamic: author
Dynamic: author-email
Dynamic: classifier
Dynamic: description
Dynamic: description-content-type
Dynamic: home-page
Dynamic: keywords
Dynamic: license
Dynamic: license-file
Dynamic: provides-extra
Dynamic: requires-dist
Dynamic: requires-python
Dynamic: summary
